{
  "adult": false,
  "backdrop_path": "/rhc8Mtuo3Kh8CndnlmTNMF8o9pU.jpg",
  "id": 1005331,
  "original_language": "en",
  "original_title": "Carry-On",
  "overview": "An airport security officer races to outsmart a mysterious traveler forcing him to let a dangerous item slip onto a Christmas Eve flight.",
  "popularity": 123.956,
  "poster_path": "/sjMN7DRi4sGiledsmllEw5HJjPy.jpg",
  "release_date": "2024-12-05",
  "title": "Carry-On",
  "video": false,
  "vote_average": 7.103,
  "vote_count": 146
}