{
  "adult": false,
  "backdrop_path": "/kkcwhgSFd81QDlXo8ytrpHPQjhy.jpg",
  "id": 1315772,
  "original_language": "en",
  "original_title": "Minions & Monsters",
  "overview": "This is the rambunctious, ridiculous and totally true story of how the Minions conquered Hollywood, became movie stars, lost everything, unleashed monsters onto the world and then banded together to try and save the planet from the mayhem they had just created.",
  "popularity": 332.1634,
  "poster_path": "/nz7i42yhLIJ4ve9JKgM6NthoLHO.jpg",
  "release_date": "2026-06-24",
  "title": "Minions & Monsters",
  "video": false,
  "vote_average": 6.4,
  "vote_count": 204
}