{
  "adult": false,
  "backdrop_path": "/wUwizGzbTk5CTiKBnE4Pq1MONwD.jpg",
  "id": 560057,
  "original_language": "en",
  "original_title": "The Sea Beast",
  "overview": "In an era when terrifying beasts roamed the seas, monster hunters were celebrated heroes. None were more beloved than the great Jacob Holland. But when young Maisie Brumble stows away on his fabled ship, he's saddled with an unexpected ally. Together they embark on an epic journey into uncharted waters and make history.",
  "popularity": 186.482,
  "poster_path": "/9Zfv4Ap1e8eKOYnZPtYaWhLkk0d.jpg",
  "release_date": "2022-06-24",
  "title": "The Sea Beast",
  "video": false,
  "vote_average": 7.521,
  "vote_count": 1114
}