{
  "adult": false,
  "backdrop_path": "/r7Dfg9aRZ78gJsmDlCirIIlNH3d.jpg",
  "id": 785084,
  "original_language": "en",
  "original_title": "The Whale",
  "overview": "A reclusive English teacher suffering from severe obesity attempts to reconnect with his estranged teenage daughter for one last chance at redemption.",
  "popularity": 641.521,
  "poster_path": "/jQ0gylJMxWSL490sy0RrPj1Lj7e.jpg",
  "release_date": "2022-12-09",
  "title": "The Whale",
  "video": false,
  "vote_average": 8.054,
  "vote_count": 1892
}