{
  "data": [
    {
      "hovertemplate": "x=%{x}\u003cbr\u003ey=%{y}\u003cbr\u003etext=%{text}\u003cextra\u003e\u003c\u002fextra\u003e",
      "legendgroup": "",
      "line": {
        "color": "#636efa",
        "dash": "solid"
      },
      "marker": {
        "symbol": "circle"
      },
      "mode": "lines+markers+text",
      "name": "",
      "orientation": "v",
      "showlegend": false,
      "text": [
        4.28,
        4.28,
        4.28,
        4.28,
        4.29,
        4.29,
        4.29,
        4.29,
        4.29,
        4.29,
        4.33,
        4.34,
        4.34,
        4.34,
        4.34,
        4.34,
        4.34,
        4.34,
        4.34,
        4.34,
        4.35,
        4.35,
        4.35,
        4.35,
        4.35,
        4.35,
        4.35,
        4.35,
        4.35,
        4.35,
        4.35,
        4.35,
        4.35,
        4.35,
        4.35,
        4.36,
        4.36,
        4.36,
        4.36,
        4.36,
        4.36,
        4.36,
        4.36,
        4.36,
        4.36,
        4.36,
        4.36,
        4.36,
        4.36,
        4.36,
        4.36,
        4.36,
        4.36,
        4.36,
        4.36,
        4.36,
        4.36,
        4.36,
        4.37,
        4.37,
        4.37
      ],
      "x": [
        "2023-03-19T19:33:11.399831",
        "2023-04-09T12:31:29.261286",
        "2023-04-23T01:40:09.804045",
        "2023-05-08T12:35:22.283427",
        "2023-05-14T01:35:38.000835",
        "2023-05-17T01:27:07.494049",
        "2023-05-27T01:26:34.557200",
        "2023-06-06T01:50:50.680294",
        "2023-06-09T12:34:39.546923",
        "2023-06-14T01:42:06.680365",
        "2023-06-20T01:37:17.539840",
        "2023-07-05T12:43:46.747317",
        "2023-07-08T01:52:12.063631",
        "2023-07-18T02:04:14.205071",
        "2023-07-26T12:34:40.677683",
        "2023-08-04T12:33:08.707992",
        "2023-08-08T12:33:36.533781",
        "2023-08-09T01:24:27.638607",
        "2023-08-17T12:31:54.991667",
        "2023-08-18T12:32:17.898931",
        "2023-09-03T01:15:26.859781",
        "2023-09-03T12:29:58.310162",
        "2023-09-07T12:33:16.532365",
        "2023-09-08T01:12:28.362664",
        "2023-09-12T12:33:32.364147",
        "2023-10-13T12:34:45.276169",
        "2023-10-24T12:33:35.531554",
        "2023-11-05T12:30:45.426337",
        "2023-11-08T01:15:10.987503",
        "2023-11-09T01:15:47.052509",
        "2023-11-19T01:22:06.034501",
        "2023-11-26T01:21:10.538606",
        "2023-12-10T12:31:17.438125",
        "2023-12-12T12:34:36.770139",
        "2023-12-21T01:16:16.821064",
        "2024-01-05T12:33:11.441172",
        "2024-01-17T12:35:01.442928",
        "2024-01-18T12:34:12.506592",
        "2024-01-24T01:19:59.875772",
        "2024-01-27T12:27:49.437771",
        "2024-01-29T01:13:19.587964",
        "2024-02-08T12:31:09.442831",
        "2024-02-09T12:30:14.313376",
        "2024-02-15T12:30:37.266060",
        "2024-02-16T01:12:52.955809",
        "2024-02-20T12:31:05.246433",
        "2024-02-21T01:12:48.766296",
        "2024-02-23T12:30:44.497415",
        "2024-02-26T12:31:21.472746",
        "2024-02-27T01:11:24.011709",
        "2024-02-28T12:30:51.505325",
        "2024-03-07T01:00:07.745660",
        "2024-03-15T12:30:58.855666",
        "2024-03-26T01:12:35.622766",
        "2024-03-30T12:28:55.979689",
        "2024-03-31T01:19:31.836966",
        "2024-04-10T01:13:42.866438",
        "2024-04-10T12:32:12.342821",
        "2024-04-12T01:14:44.552164",
        "2024-04-19T01:15:19.876058",
        "2024-04-28T12:33:00.083599"
      ],
      "xaxis": "x",
      "y": [
        4.28,
        4.28,
        4.28,
        4.28,
        4.29,
        4.29,
        4.29,
        4.29,
        4.29,
        4.29,
        4.33,
        4.34,
        4.34,
        4.34,
        4.34,
        4.34,
        4.34,
        4.34,
        4.34,
        4.34,
        4.35,
        4.35,
        4.35,
        4.35,
        4.35,
        4.35,
        4.35,
        4.35,
        4.35,
        4.35,
        4.35,
        4.35,
        4.35,
        4.35,
        4.35,
        4.36,
        4.36,
        4.36,
        4.36,
        4.36,
        4.36,
        4.36,
        4.36,
        4.36,
        4.36,
        4.36,
        4.36,
        4.36,
        4.36,
        4.36,
        4.36,
        4.36,
        4.36,
        4.36,
        4.36,
        4.36,
        4.36,
        4.36,
        4.37,
        4.37,
        4.37
      ],
      "yaxis": "y",
      "type": "scatter",
      "textposition": "bottom right"
    }
  ],
  "layout": {
    "template": {
      "data": {
        "histogram2dcontour": [
          {
            "type": "histogram2dcontour",
            "colorbar": {
              "outlinewidth": 0,
              "ticks": ""
            },
            "colorscale": [
              [
                0.0,
                "#0d0887"
              ],
              [
                0.1111111111111111,
                "#46039f"
              ],
              [
                0.2222222222222222,
                "#7201a8"
              ],
              [
                0.3333333333333333,
                "#9c179e"
              ],
              [
                0.4444444444444444,
                "#bd3786"
              ],
              [
                0.5555555555555556,
                "#d8576b"
              ],
              [
                0.6666666666666666,
                "#ed7953"
              ],
              [
                0.7777777777777778,
                "#fb9f3a"
              ],
              [
                0.8888888888888888,
                "#fdca26"
              ],
              [
                1.0,
                "#f0f921"
              ]
            ]
          }
        ],
        "choropleth": [
          {
            "type": "choropleth",
            "colorbar": {
              "outlinewidth": 0,
              "ticks": ""
            }
          }
        ],
        "histogram2d": [
          {
            "type": "histogram2d",
            "colorbar": {
              "outlinewidth": 0,
              "ticks": ""
            },
            "colorscale": [
              [
                0.0,
                "#0d0887"
              ],
              [
                0.1111111111111111,
                "#46039f"
              ],
              [
                0.2222222222222222,
                "#7201a8"
              ],
              [
                0.3333333333333333,
                "#9c179e"
              ],
              [
                0.4444444444444444,
                "#bd3786"
              ],
              [
                0.5555555555555556,
                "#d8576b"
              ],
              [
                0.6666666666666666,
                "#ed7953"
              ],
              [
                0.7777777777777778,
                "#fb9f3a"
              ],
              [
                0.8888888888888888,
                "#fdca26"
              ],
              [
                1.0,
                "#f0f921"
              ]
            ]
          }
        ],
        "heatmap": [
          {
            "type": "heatmap",
            "colorbar": {
              "outlinewidth": 0,
              "ticks": ""
            },
            "colorscale": [
              [
                0.0,
                "#0d0887"
              ],
              [
                0.1111111111111111,
                "#46039f"
              ],
              [
                0.2222222222222222,
                "#7201a8"
              ],
              [
                0.3333333333333333,
                "#9c179e"
              ],
              [
                0.4444444444444444,
                "#bd3786"
              ],
              [
                0.5555555555555556,
                "#d8576b"
              ],
              [
                0.6666666666666666,
                "#ed7953"
              ],
              [
                0.7777777777777778,
                "#fb9f3a"
              ],
              [
                0.8888888888888888,
                "#fdca26"
              ],
              [
                1.0,
                "#f0f921"
              ]
            ]
          }
        ],
        "heatmapgl": [
          {
            "type": "heatmapgl",
            "colorbar": {
              "outlinewidth": 0,
              "ticks": ""
            },
            "colorscale": [
              [
                0.0,
                "#0d0887"
              ],
              [
                0.1111111111111111,
                "#46039f"
              ],
              [
                0.2222222222222222,
                "#7201a8"
              ],
              [
                0.3333333333333333,
                "#9c179e"
              ],
              [
                0.4444444444444444,
                "#bd3786"
              ],
              [
                0.5555555555555556,
                "#d8576b"
              ],
              [
                0.6666666666666666,
                "#ed7953"
              ],
              [
                0.7777777777777778,
                "#fb9f3a"
              ],
              [
                0.8888888888888888,
                "#fdca26"
              ],
              [
                1.0,
                "#f0f921"
              ]
            ]
          }
        ],
        "contourcarpet": [
          {
            "type": "contourcarpet",
            "colorbar": {
              "outlinewidth": 0,
              "ticks": ""
            }
          }
        ],
        "contour": [
          {
            "type": "contour",
            "colorbar": {
              "outlinewidth": 0,
              "ticks": ""
            },
            "colorscale": [
              [
                0.0,
                "#0d0887"
              ],
              [
                0.1111111111111111,
                "#46039f"
              ],
              [
                0.2222222222222222,
                "#7201a8"
              ],
              [
                0.3333333333333333,
                "#9c179e"
              ],
              [
                0.4444444444444444,
                "#bd3786"
              ],
              [
                0.5555555555555556,
                "#d8576b"
              ],
              [
                0.6666666666666666,
                "#ed7953"
              ],
              [
                0.7777777777777778,
                "#fb9f3a"
              ],
              [
                0.8888888888888888,
                "#fdca26"
              ],
              [
                1.0,
                "#f0f921"
              ]
            ]
          }
        ],
        "surface": [
          {
            "type": "surface",
            "colorbar": {
              "outlinewidth": 0,
              "ticks": ""
            },
            "colorscale": [
              [
                0.0,
                "#0d0887"
              ],
              [
                0.1111111111111111,
                "#46039f"
              ],
              [
                0.2222222222222222,
                "#7201a8"
              ],
              [
                0.3333333333333333,
                "#9c179e"
              ],
              [
                0.4444444444444444,
                "#bd3786"
              ],
              [
                0.5555555555555556,
                "#d8576b"
              ],
              [
                0.6666666666666666,
                "#ed7953"
              ],
              [
                0.7777777777777778,
                "#fb9f3a"
              ],
              [
                0.8888888888888888,
                "#fdca26"
              ],
              [
                1.0,
                "#f0f921"
              ]
            ]
          }
        ],
        "mesh3d": [
          {
            "type": "mesh3d",
            "colorbar": {
              "outlinewidth": 0,
              "ticks": ""
            }
          }
        ],
        "scatter": [
          {
            "fillpattern": {
              "fillmode": "overlay",
              "size": 10,
              "solidity": 0.2
            },
            "type": "scatter"
          }
        ],
        "parcoords": [
          {
            "type": "parcoords",
            "line": {
              "colorbar": {
                "outlinewidth": 0,
                "ticks": ""
              }
            }
          }
        ],
        "scatterpolargl": [
          {
            "type": "scatterpolargl",
            "marker": {
              "colorbar": {
                "outlinewidth": 0,
                "ticks": ""
              }
            }
          }
        ],
        "bar": [
          {
            "error_x": {
              "color": "#2a3f5f"
            },
            "error_y": {
              "color": "#2a3f5f"
            },
            "marker": {
              "line": {
                "color": "#E5ECF6",
                "width": 0.5
              },
              "pattern": {
                "fillmode": "overlay",
                "size": 10,
                "solidity": 0.2
              }
            },
            "type": "bar"
          }
        ],
        "scattergeo": [
          {
            "type": "scattergeo",
            "marker": {
              "colorbar": {
                "outlinewidth": 0,
                "ticks": ""
              }
            }
          }
        ],
        "scatterpolar": [
          {
            "type": "scatterpolar",
            "marker": {
              "colorbar": {
                "outlinewidth": 0,
                "ticks": ""
              }
            }
          }
        ],
        "histogram": [
          {
            "marker": {
              "pattern": {
                "fillmode": "overlay",
                "size": 10,
                "solidity": 0.2
              }
            },
            "type": "histogram"
          }
        ],
        "scattergl": [
          {
            "type": "scattergl",
            "marker": {
              "colorbar": {
                "outlinewidth": 0,
                "ticks": ""
              }
            }
          }
        ],
        "scatter3d": [
          {
            "type": "scatter3d",
            "line": {
              "colorbar": {
                "outlinewidth": 0,
                "ticks": ""
              }
            },
            "marker": {
              "colorbar": {
                "outlinewidth": 0,
                "ticks": ""
              }
            }
          }
        ],
        "scattermapbox": [
          {
            "type": "scattermapbox",
            "marker": {
              "colorbar": {
                "outlinewidth": 0,
                "ticks": ""
              }
            }
          }
        ],
        "scatterternary": [
          {
            "type": "scatterternary",
            "marker": {
              "colorbar": {
                "outlinewidth": 0,
                "ticks": ""
              }
            }
          }
        ],
        "scattercarpet": [
          {
            "type": "scattercarpet",
            "marker": {
              "colorbar": {
                "outlinewidth": 0,
                "ticks": ""
              }
            }
          }
        ],
        "carpet": [
          {
            "aaxis": {
              "endlinecolor": "#2a3f5f",
              "gridcolor": "white",
              "linecolor": "white",
              "minorgridcolor": "white",
              "startlinecolor": "#2a3f5f"
            },
            "baxis": {
              "endlinecolor": "#2a3f5f",
              "gridcolor": "white",
              "linecolor": "white",
              "minorgridcolor": "white",
              "startlinecolor": "#2a3f5f"
            },
            "type": "carpet"
          }
        ],
        "table": [
          {
            "cells": {
              "fill": {
                "color": "#EBF0F8"
              },
              "line": {
                "color": "white"
              }
            },
            "header": {
              "fill": {
                "color": "#C8D4E3"
              },
              "line": {
                "color": "white"
              }
            },
            "type": "table"
          }
        ],
        "barpolar": [
          {
            "marker": {
              "line": {
                "color": "#E5ECF6",
                "width": 0.5
              },
              "pattern": {
                "fillmode": "overlay",
                "size": 10,
                "solidity": 0.2
              }
            },
            "type": "barpolar"
          }
        ],
        "pie": [
          {
            "automargin": true,
            "type": "pie"
          }
        ]
      },
      "layout": {
        "autotypenumbers": "strict",
        "colorway": [
          "#636efa",
          "#EF553B",
          "#00cc96",
          "#ab63fa",
          "#FFA15A",
          "#19d3f3",
          "#FF6692",
          "#B6E880",
          "#FF97FF",
          "#FECB52"
        ],
        "font": {
          "color": "#2a3f5f"
        },
        "hovermode": "closest",
        "hoverlabel": {
          "align": "left"
        },
        "paper_bgcolor": "white",
        "plot_bgcolor": "#E5ECF6",
        "polar": {
          "bgcolor": "#E5ECF6",
          "angularaxis": {
            "gridcolor": "white",
            "linecolor": "white",
            "ticks": ""
          },
          "radialaxis": {
            "gridcolor": "white",
            "linecolor": "white",
            "ticks": ""
          }
        },
        "ternary": {
          "bgcolor": "#E5ECF6",
          "aaxis": {
            "gridcolor": "white",
            "linecolor": "white",
            "ticks": ""
          },
          "baxis": {
            "gridcolor": "white",
            "linecolor": "white",
            "ticks": ""
          },
          "caxis": {
            "gridcolor": "white",
            "linecolor": "white",
            "ticks": ""
          }
        },
        "coloraxis": {
          "colorbar": {
            "outlinewidth": 0,
            "ticks": ""
          }
        },
        "colorscale": {
          "sequential": [
            [
              0.0,
              "#0d0887"
            ],
            [
              0.1111111111111111,
              "#46039f"
            ],
            [
              0.2222222222222222,
              "#7201a8"
            ],
            [
              0.3333333333333333,
              "#9c179e"
            ],
            [
              0.4444444444444444,
              "#bd3786"
            ],
            [
              0.5555555555555556,
              "#d8576b"
            ],
            [
              0.6666666666666666,
              "#ed7953"
            ],
            [
              0.7777777777777778,
              "#fb9f3a"
            ],
            [
              0.8888888888888888,
              "#fdca26"
            ],
            [
              1.0,
              "#f0f921"
            ]
          ],
          "sequentialminus": [
            [
              0.0,
              "#0d0887"
            ],
            [
              0.1111111111111111,
              "#46039f"
            ],
            [
              0.2222222222222222,
              "#7201a8"
            ],
            [
              0.3333333333333333,
              "#9c179e"
            ],
            [
              0.4444444444444444,
              "#bd3786"
            ],
            [
              0.5555555555555556,
              "#d8576b"
            ],
            [
              0.6666666666666666,
              "#ed7953"
            ],
            [
              0.7777777777777778,
              "#fb9f3a"
            ],
            [
              0.8888888888888888,
              "#fdca26"
            ],
            [
              1.0,
              "#f0f921"
            ]
          ],
          "diverging": [
            [
              0,
              "#8e0152"
            ],
            [
              0.1,
              "#c51b7d"
            ],
            [
              0.2,
              "#de77ae"
            ],
            [
              0.3,
              "#f1b6da"
            ],
            [
              0.4,
              "#fde0ef"
            ],
            [
              0.5,
              "#f7f7f7"
            ],
            [
              0.6,
              "#e6f5d0"
            ],
            [
              0.7,
              "#b8e186"
            ],
            [
              0.8,
              "#7fbc41"
            ],
            [
              0.9,
              "#4d9221"
            ],
            [
              1,
              "#276419"
            ]
          ]
        },
        "xaxis": {
          "gridcolor": "white",
          "linecolor": "white",
          "ticks": "",
          "title": {
            "standoff": 15
          },
          "zerolinecolor": "white",
          "automargin": true,
          "zerolinewidth": 2
        },
        "yaxis": {
          "gridcolor": "white",
          "linecolor": "white",
          "ticks": "",
          "title": {
            "standoff": 15
          },
          "zerolinecolor": "white",
          "automargin": true,
          "zerolinewidth": 2
        },
        "scene": {
          "xaxis": {
            "backgroundcolor": "#E5ECF6",
            "gridcolor": "white",
            "linecolor": "white",
            "showbackground": true,
            "ticks": "",
            "zerolinecolor": "white",
            "gridwidth": 2
          },
          "yaxis": {
            "backgroundcolor": "#E5ECF6",
            "gridcolor": "white",
            "linecolor": "white",
            "showbackground": true,
            "ticks": "",
            "zerolinecolor": "white",
            "gridwidth": 2
          },
          "zaxis": {
            "backgroundcolor": "#E5ECF6",
            "gridcolor": "white",
            "linecolor": "white",
            "showbackground": true,
            "ticks": "",
            "zerolinecolor": "white",
            "gridwidth": 2
          }
        },
        "shapedefaults": {
          "line": {
            "color": "#2a3f5f"
          }
        },
        "annotationdefaults": {
          "arrowcolor": "#2a3f5f",
          "arrowhead": 0,
          "arrowwidth": 1
        },
        "geo": {
          "bgcolor": "white",
          "landcolor": "#E5ECF6",
          "subunitcolor": "white",
          "showland": true,
          "showlakes": true,
          "lakecolor": "white"
        },
        "title": {
          "x": 0.05
        },
        "mapbox": {
          "style": "light"
        }
      }
    },
    "xaxis": {
      "anchor": "y",
      "domain": [
        0.0,
        1.0
      ],
      "title": {
        "text": "x"
      }
    },
    "yaxis": {
      "anchor": "x",
      "domain": [
        0.0,
        1.0
      ],
      "title": {
        "text": "y"
      }
    },
    "legend": {
      "tracegroupgap": 0
    },
    "title": {
      "text": "the-pianist"
    }
  }
}